statlorem.py
statlorem-0.5.0.dist-info/WHEEL
statlorem-0.5.0.dist-info/DESCRIPTION.rst
statlorem-0.5.0.dist-info/top_level.txt
statlorem-0.5.0.dist-info/metadata.json
statlorem-0.5.0.dist-info/METADATA
statlorem-0.5.0.dist-info/RECORD
