Metadata-Version: 2.0
Name: statlorem
Version: 0.5.0
Summary: Fun and quirky Lorem Ipsum!
Home-page: https://github.com/jesuscast/Statistical-Lorem
Author: Jesus Andres Castaneda Sosa
Author-email: jesus.cast.sosa@gmail.com
License: MIT
Keywords: markov lorem ipsum generator
Platform: UNKNOWN
Classifier: Development Status :: 5 - Production/Stable
Classifier: Intended Audience :: Developers
Classifier: Topic :: Software Development :: Build Tools
Classifier: License :: OSI Approved :: MIT License
Classifier: Programming Language :: Python :: 2
Classifier: Programming Language :: Python :: 2.6
Classifier: Programming Language :: Python :: 2.7
Requires-Dist: numpy
